mostlyai/engine/__init__.py
mostlyai/engine/_common.py
mostlyai/engine/_dtypes.py
mostlyai/engine/_memory.py
mostlyai/engine/_training_utils.py
mostlyai/engine/_workspace.py
mostlyai/engine/analysis.py
mostlyai/engine/domain.py
mostlyai/engine/encoding.py
mostlyai/engine/generation.py
mostlyai/engine/logging.py
mostlyai/engine/random_state.py
mostlyai/engine/splitting.py
mostlyai/engine/training.py
mostlyai/engine/_encoding_types/__init__.py
mostlyai/engine/_encoding_types/language/__init__.py
mostlyai/engine/_encoding_types/language/categorical.py
mostlyai/engine/_encoding_types/language/datetime.py
mostlyai/engine/_encoding_types/language/numeric.py
mostlyai/engine/_encoding_types/language/text.py
mostlyai/engine/_encoding_types/tabular/__init__.py
mostlyai/engine/_encoding_types/tabular/categorical.py
mostlyai/engine/_encoding_types/tabular/character.py
mostlyai/engine/_encoding_types/tabular/datetime.py
mostlyai/engine/_encoding_types/tabular/itt.py
mostlyai/engine/_encoding_types/tabular/lat_long.py
mostlyai/engine/_encoding_types/tabular/numeric.py
mostlyai/engine/_language/__init__.py
mostlyai/engine/_language/common.py
mostlyai/engine/_language/encoding.py
mostlyai/engine/_language/generation.py
mostlyai/engine/_language/interface.py
mostlyai/engine/_language/lstm.py
mostlyai/engine/_language/tokenizer_utils.py
mostlyai/engine/_language/training.py
mostlyai/engine/_language/xgrammar_utils.py
mostlyai/engine/_language/engine/__init__.py
mostlyai/engine/_language/engine/base.py
mostlyai/engine/_language/engine/hf_engine.py
mostlyai/engine/_language/engine/vllm_engine.py
mostlyai/engine/_tabular/__init__.py
mostlyai/engine/_tabular/argn.py
mostlyai/engine/_tabular/common.py
mostlyai/engine/_tabular/encoding.py
mostlyai/engine/_tabular/fairness.py
mostlyai/engine/_tabular/generation.py
mostlyai/engine/_tabular/interface.py
mostlyai/engine/_tabular/probability.py
mostlyai/engine/_tabular/training.py
mostlyai_engine-2.4.0.dist-info/METADATA
mostlyai_engine-2.4.0.dist-info/WHEEL
mostlyai_engine-2.4.0.dist-info/licenses/LICENSE
mostlyai_engine-2.4.0.dist-info/RECORD
