Metadata-Version: 2.4
Name: mostlyai-engine
Version: 2.4.0
Summary: Synthetic Data Engine
Project-URL: homepage, https://github.com/mostly-ai/mostlyai-engine
Project-URL: repository, https://github.com/mostly-ai/mostlyai-engine
Project-URL: documentation, https://mostly-ai.github.io/mostlyai-engine/
Author-email: MOSTLY AI <dev@mostly.ai>
License-Expression: Apache-2.0
License-File: LICENSE
Classifier: Development Status :: 5 - Production/Stable
Classifier: Intended Audience :: Developers
Classifier: Intended Audience :: Financial and Insurance Industry
Classifier: Intended Audience :: Healthcare Industry
Classifier: Intended Audience :: Information Technology
Classifier: Intended Audience :: Science/Research
Classifier: Intended Audience :: Telecommunications Industry
Classifier: License :: OSI Approved :: Apache Software License
Classifier: Operating System :: OS Independent
Classifier: Programming Language :: Python :: 3.10
Classifier: Programming Language :: Python :: 3.11
Classifier: Programming Language :: Python :: 3.12
Classifier: Programming Language :: Python :: 3.13
Classifier: Topic :: Software Development :: Libraries
Classifier: Typing :: Typed
Requires-Python: >=3.10
Requires-Dist: accelerate>=1.5.0
Requires-Dist: datasets>=3.0.0
Requires-Dist: huggingface-hub[hf-xet]>=0.30.2
Requires-Dist: joblib>=1.4.2
Requires-Dist: json-repair>=0.47.0
Requires-Dist: numpy>=2.0.0
Requires-Dist: opacus>=1.5.4
Requires-Dist: pandas>=2.2.0
Requires-Dist: peft>=0.12.0
Requires-Dist: psutil<6,>=5.9.5
Requires-Dist: pyarrow>=16.0.0
Requires-Dist: scikit-learn>=1.4.0
Requires-Dist: setuptools>=77.0.3
Requires-Dist: tokenizers>=0.21.0
Requires-Dist: torch<2.10.0,>=2.9.0
Requires-Dist: torchaudio<2.10.0,>=2.9.0
Requires-Dist: torchvision<0.25.0,>=0.24.0
Requires-Dist: transformers>=4.55.0
Requires-Dist: xgrammar>=0.1.21
Provides-Extra: gpu
Requires-Dist: bitsandbytes==0.42.0; (sys_platform == 'darwin') and extra == 'gpu'
Requires-Dist: bitsandbytes>=0.45.5; (sys_platform == 'linux') and extra == 'gpu'
Requires-Dist: vllm==0.12.0; (sys_platform == 'linux' or sys_platform == 'darwin') and extra == 'gpu'
